cyber_sdk/__init__.py
cyber_sdk/client/__init__.py
cyber_sdk/client/lcd/__init__.py
cyber_sdk/client/lcd/api/__init__.py
cyber_sdk/client/lcd/api/_base.py
cyber_sdk/client/lcd/api/auth.py
cyber_sdk/client/lcd/api/authz.py
cyber_sdk/client/lcd/api/bank.py
cyber_sdk/client/lcd/api/distribution.py
cyber_sdk/client/lcd/api/feegrant.py
cyber_sdk/client/lcd/api/gov.py
cyber_sdk/client/lcd/api/graph.py
cyber_sdk/client/lcd/api/ibc.py
cyber_sdk/client/lcd/api/ibc_transfer.py
cyber_sdk/client/lcd/api/liquidity.py
cyber_sdk/client/lcd/api/mint.py
cyber_sdk/client/lcd/api/oracle.py
cyber_sdk/client/lcd/api/rank.py
cyber_sdk/client/lcd/api/slashing.py
cyber_sdk/client/lcd/api/staking.py
cyber_sdk/client/lcd/api/tendermint.py
cyber_sdk/client/lcd/api/treasury.py
cyber_sdk/client/lcd/api/tx.py
cyber_sdk/client/lcd/api/wasm.py
cyber_sdk/client/lcd/lcdclient.py
cyber_sdk/client/lcd/lcdutils.py
cyber_sdk/client/lcd/params.py
cyber_sdk/client/lcd/wallet.py
cyber_sdk/client/localbostrom.py
cyber_sdk/core/__init__.py
cyber_sdk/core/auth/__init__.py
cyber_sdk/core/auth/data/__init__.py
cyber_sdk/core/auth/data/account.py
cyber_sdk/core/auth/data/base_account.py
cyber_sdk/core/auth/data/base_periodic_vesting_account.py
cyber_sdk/core/auth/data/base_vesting_account.py
cyber_sdk/core/auth/data/lazy_graded_vesting_account.py
cyber_sdk/core/authz/__init__.py
cyber_sdk/core/authz/data.py
cyber_sdk/core/authz/msgs.py
cyber_sdk/core/bank/__init__.py
cyber_sdk/core/bank/msgs.py
cyber_sdk/core/bech32.py
cyber_sdk/core/block.py
cyber_sdk/core/broadcast.py
cyber_sdk/core/coin.py
cyber_sdk/core/coins.py
cyber_sdk/core/compact_bit_array.py
cyber_sdk/core/deposit.py
cyber_sdk/core/distribution/__init__.py
cyber_sdk/core/distribution/msgs.py
cyber_sdk/core/distribution/proposals.py
cyber_sdk/core/fee.py
cyber_sdk/core/feegrant/__init__.py
cyber_sdk/core/feegrant/data.py
cyber_sdk/core/feegrant/msgs.py
cyber_sdk/core/gov/__init__.py
cyber_sdk/core/gov/data.py
cyber_sdk/core/gov/msgs.py
cyber_sdk-1.1.2.dist-info/LICENSE
cyber_sdk-1.1.2.dist-info/WHEEL
cyber_sdk-1.1.2.dist-info/METADATA
cyber_sdk-1.1.2.dist-info/RECORD
